[
  {
    "type": "function",
    "name": "create",
    "inputs": [
      {
        "name": "initialSupply",
        "type": "uint256",
        "internalType": "uint256"
      },
      {
        "name": "recipient",
        "type": "address",
        "internalType": "address"
      },
      {
        "name": "owner",
        "type": "address",
        "internalType": "address"
      },
      {
        "name": "salt",
        "type": "bytes32",
        "internalType": "bytes32"
      },
      {
        "name": "tokenData",
        "type": "bytes",
        "internalType": "bytes"
      }
    ],
    "outputs": [
      {
        "name": "token",
        "type": "address",
        "internalType": "address"
      }
    ],
    "stateMutability": "nonpayable"
  },
  {
    "type": "function",
    "name": "isDeployedToken",
    "inputs": [
      {
        "name": "token",
        "type": "address",
        "internalType": "address"
      }
    ],
    "outputs": [
      {
        "name": "",
        "type": "bool",
        "internalType": "bool"
      }
    ],
    "stateMutability": "view"
  },
  {
    "type": "function",
    "name": "isTokenCreator",
    "inputs": [
      {
        "name": "token",
        "type": "address",
        "internalType": "address"
      },
      {
        "name": "user",
        "type": "address",
        "internalType": "address"
      }
    ],
    "outputs": [
      {
        "name": "",
        "type": "bool",
        "internalType": "bool"
      }
    ],
    "stateMutability": "view"
  }
]
